jxon/__init__.py
jxon/combined.py
jxon/jxon.py
jxon/jxontype.py
jxon/jxsd.py
jxon/parser.py
jxon-1.0.3.dist-info/METADATA
jxon-1.0.3.dist-info/WHEEL
jxon-1.0.3.dist-info/top_level.txt
jxon-1.0.3.dist-info/RECORD
