Metadata-Version: 2.1
Name: jxon
Version: 1.0.3
Summary: JSON++
Home-page: https://github.com/cstuartroe/jxon
Author: Conor Stuart Roe
Author-email: conorstuartroe@gmail.com
License: MIT
Platform: UNKNOWN
Classifier: License :: OSI Approved :: MIT License
Classifier: Programming Language :: Python :: 3
